GrabWinPy/GrabWinPy.py
GrabWinPy/__init__.py
GrabWinPy-1.0.4.dist-info/METADATA
GrabWinPy-1.0.4.dist-info/WHEEL
GrabWinPy-1.0.4.dist-info/top_level.txt
GrabWinPy-1.0.4.dist-info/RECORD
